django_admin_page_api/__init__.py
django_admin_page_api/apps.py
django_admin_page_api/model_functions.py
django_admin_page_api/sites.py
django_admin_page_api/urls.py
django_admin_page_api/utils.py
django_admin_page_api/views.py
django_admin_page_api-1.3.1.dist-info/LICENSE
django_admin_page_api-1.3.1.dist-info/METADATA
django_admin_page_api-1.3.1.dist-info/WHEEL
django_admin_page_api-1.3.1.dist-info/top_level.txt
django_admin_page_api-1.3.1.dist-info/RECORD
