Metadata-Version: 2.1
Name: django_admin_page_api
Version: 1.3.1
Summary: Django Admin Page API
Home-page: https://github.com/mateuszzebala/django-admin-page-api
Author: Mateusz Zębala
Author-email: mateusz.zebala.pl@gmail.com
License: MIT
Classifier: License :: OSI Approved :: MIT License
Classifier: Programming Language :: Python :: 3
Classifier: Programming Language :: Python :: 3.7
Classifier: Programming Language :: Python :: 3.8
Classifier: Programming Language :: Python :: 3.9
Classifier: Programming Language :: Python :: 3.10
Classifier: Programming Language :: Python :: 3.11
License-File: LICENSE
Requires-Dist: django
